endersgame/__init__.py
endersgame/gameconfig.py
endersgame/accounting/__init__.py
endersgame/accounting/pnl.py
endersgame/accounting/pnlutil.py
endersgame/accounting/stdsignalpnl.py
endersgame/attackers/__init__.py
endersgame/attackers/attacker.py
endersgame/attackers/attackerwithhistorymixin.py
endersgame/attackers/attackerwithpnl.py
endersgame/attackers/baseattacker.py
endersgame/attackers/calibratedattacker.py
endersgame/datasources/__init__.py
endersgame/datasources/streamgenerator.py
endersgame/datasources/streamgeneratorgenerator.py
endersgame/datasources/streamurl.py
endersgame/examples/__init__.py
endersgame/examples/calibratedmacdattacker.py
endersgame/examples/empiricalmeanreversionattacker.py
endersgame/examples/macdattacker.py
endersgame/examples/meanreversionattacker.py
endersgame/examples/randomattackerwithpnl.py
endersgame/mixins/__init__.py
endersgame/mixins/historymixin.py
endersgame/riverstats/__init__.py
endersgame/riverstats/fewmean.py
endersgame/riverstats/fewvar.py
endersgame/rivertransformers/__init__.py
endersgame/rivertransformers/macd.py
endersgame/runners/__init__.py
endersgame/runners/forgetfulrunner.py
endersgame/syntheticdata/__init__.py
endersgame/syntheticdata/momentumregimes.py
endersgame-1.0.1.dist-info/LICENSE
endersgame-1.0.1.dist-info/METADATA
endersgame-1.0.1.dist-info/WHEEL
endersgame-1.0.1.dist-info/entry_points.txt
endersgame-1.0.1.dist-info/top_level.txt
endersgame-1.0.1.dist-info/RECORD
